[
  {
    "id": 631026,
    "name": "Priyank Solanki ",
    "username": "Priyank",
    "avatar_template": "/user_avatar/discourse.onlinedegree.iitm.ac.in/priyank/{size}/66833_2.png",
    "created_at": "2025-05-25T10:42:16.599Z",
    "cooked": "<p>I am writing to clarify which email ID should be associated with my GitHub account for the graded assignment in the TDS course. Would it be better to use my IITM academic email address (iitm.ac.in) or my personal email address for the submission?</p>",
    "post_number": 1,
    "post_type": 1,
    "posts_count": 2,
    "updated_at": "2025-05-25T10:42:16.599Z",
    "reply_count": 0,
    "reply_to_post_number": null,
    "quote_count": 0,
    "incoming_link_count": 1,
    "reads": 44,
    "readers_count": 43,
    "score": 22.0,
    "yours": false,
    "topic_id": 176323,
    "topic_slug": "clarification-on-email-id-for-github-account-submission-for-tds-course-assignment",
    "display_username": "Priyank Solanki ",
    "primary_group_name": "ds-students",
    "flair_name": "ds-students",
    "flair_url": null,
    "flair_bg_color": "",
    "flair_color": "",
    "flair_group_id": 294,
    "badges_granted": [],
    "version": 1,
    "can_edit": false,
    "can_delete": false,
    "can_recover": false,
    "can_see_hidden_post": false,
    "can_wiki": false,
    "read": false,
    "user_title": null,
    "bookmarked": false,
    "actions_summary": [
      {
        "id": 2,
        "count": 1,
        "can_act": true
      }
    ],
    "moderator": false,
    "admin": false,
    "staff": false,
    "user_id": 19016,
    "hidden": false,
    "trust_level": 0,
    "deleted_at": null,
    "user_deleted": false,
    "edit_reason": null,
    "can_view_edit_history": true,
    "wiki": false,
    "post_url": "/t/clarification-on-email-id-for-github-account-submission-for-tds-course-assignment/176323/1",
    "user_cakedate": "2023-06-06",
    "reactions": [
      {
        "id": "heart",
        "type": "emoji",
        "count": 1
      }
    ],
    "current_user_reaction": null,
    "reaction_users_count": 1,
    "current_user_used_main_reaction": false,
    "can_accept_answer": false,
    "can_unaccept_answer": false,
    "accepted_answer": false,
    "topic_accepted_answer": null,
    "can_vote": false
  },
  {
    "id": 631064,
    "name": "Sanvi Sneh",
    "username": "22f3003023",
    "avatar_template": "/user_avatar/discourse.onlinedegree.iitm.ac.in/22f3003023/{size}/119245_2.png",
    "created_at": "2025-05-25T11:12:21.484Z",
    "cooked": "<p>You can use any mail id for creating the GitHub Account.</p>",
    "post_number": 2,
    "post_type": 1,
    "posts_count": 2,
    "updated_at": "2025-05-25T11:12:21.484Z",
    "reply_count": 0,
    "reply_to_post_number": null,
    "quote_count": 0,
    "incoming_link_count": 0,
    "reads": 42,
    "readers_count": 41,
    "score": 6.6,
    "yours": false,
    "topic_id": 176323,
    "topic_slug": "clarification-on-email-id-for-github-account-submission-for-tds-course-assignment",
    "display_username": "Sanvi Sneh",
    "primary_group_name": "ds-students",
    "flair_name": "ds-students",
    "flair_url": null,
    "flair_bg_color": "",
    "flair_color": "",
    "flair_group_id": 294,
    "badges_granted": [],
    "version": 1,
    "can_edit": false,
    "can_delete": false,
    "can_recover": false,
    "can_see_hidden_post": false,
    "can_wiki": false,
    "read": false,
    "user_title": null,
    "bookmarked": false,
    "actions_summary": [
      {
        "id": 2,
        "can_act": true
      }
    ],
    "moderator": false,
    "admin": false,
    "staff": false,
    "user_id": 16656,
    "hidden": false,
    "trust_level": 0,
    "deleted_at": null,
    "user_deleted": false,
    "edit_reason": null,
    "can_view_edit_history": true,
    "wiki": false,
    "post_url": "/t/clarification-on-email-id-for-github-account-submission-for-tds-course-assignment/176323/2",
    "user_cakedate": "2023-02-01",
    "reactions": [],
    "current_user_reaction": null,
    "reaction_users_count": 0,
    "current_user_used_main_reaction": false,
    "can_accept_answer": false,
    "can_unaccept_answer": false,
    "accepted_answer": false,
    "topic_accepted_answer": null
  }
]